Metadata-Version: 1.0
Name: dnsdtest
Version: 0.1
Summary: Gaussian distributions
Home-page: UNKNOWN
Author: Mamadou Bousso
Author-email: mbousso@univ-thies.sn
License: UNKNOWN
Platform: UNKNOWN
